{
    "id": 93251082,
    "name": "banned",
    "author": "GeoDom85yt",
    "creators": [],
    "verifier": "GeoDom85YT",
    "verification": "https://youtu.be/QlXamlYvJtQ?si=xUxyX_Wov79ySMxH",
    "percentToQualify": 100,
    "records": [],
    "tags": ["Epilepsy Warning", "Short", "GDPS Level", "NoNG Song"],
    "song": "https://cdn.discordapp.com/attachments/1112151604070719699/1173022100466978886/1218618.mp3?ex=656270f6&is=654ffbf6&hm=e9ff01f94036084378b0c532fc0ca5bd6101a1b4779fddef3aea33ad324d8c58&"
}
