{
    "id": 61775814,
    "name": "Element 111 Rg",
    "author": "Compendium",
    "creators": ["DarkX", "Restoration Union"],
    "verifier": "paqoe",
    "verification": "https://youtu.be/ZcdiTGuIJ1k?si=LrHyHzTwDh9GWd1j",
    "percentToQualify": 47,
    "password": "Free to copy",
    "records": [
        {
            "user": "Mike",
            "link": "https://www.youtube.com/watch?v=TpNN1bkNsiw&t=24s",
            "percent": 100
        }
    ],
    "tags": ["CBF", "Old Impossible Level"]
}
