{
    "id": 79617131,
    "name": "RAIN (Remake)",
    "author": "ImPhara",
    "creators": ["Skyyee", "TrobezB", "Qtr-chan", "Rubenkraak", "Retaliate", "Mr Ramen", "Patch N0w0b", "nCarver", "Sneze", "Jce", "Fenkoo", "zion"],
    "verifier": "Wolvez",
    "verification": "https://youtu.be/-6AOn-o7mQo",
    "showcase": "https://www.youtube.com/watch?v=4Vfx47dWd58",
    "percentToQualify": 100,
    "records": [
        {
	        "user": "Tizetre",
	        "link": "https://youtu.be/OKxh2kKrtfE",
	        "percent": 100
	    },
        {
	        "user": "stormyy",
	        "link": "https://youtu.be/4tQJetfaiq0",
	        "percent": 100
	    },
        {
	        "user": "Donei GD",
	        "link": "https://youtu.be/-MuKy7YTSP8",
	        "percent": 100
	    },
        {
	        "user": "Rubix",
	        "link": "https://youtu.be/jNMsaV7Co9M",
	        "percent": 100
	    },
        {
            "user": "jalive",
            "link": "https://www.youtube.com/watch?v=ToPeikScWXs",
            "percent": 100
        },
        {
	        "user": "Sealio",
	        "link": "https://youtu.be/vN7xk2ayTHQ",
	        "percent": 100
        },
        {
            "user": "ZildexGD",
	        "link": "https://www.youtube.com/watch?v=WSTmK_w0Rpw",
	        "percent": 100
	    },
        {
            "user": "zGabriel",
	        "link": "https://youtu.be/6RAaU_Osu_Y?si=lZ6rNV1DBlVGMA4m",
	        "percent": 100
        }, 
        {
            "user": "DarkScylla", 
            "link": "https://youtu.be/p_jLm00JwIo?si=9pMCJoFs-0feg4hf", 
            "percent": 100
	    }, 
        {
            "user": "Hipo", 
            "link": "https://youtube.com/watch?v=fWGqJWPsf9k&si=6QmHOi7e59cU2Vd0", 
            "percent": 100
        },
        {
            "user": "Magic", 
            "link": "https://youtu.be/tdz7CbSFpPA?si=jiKVWt5R03EcvU-6", 
            "percent": 100
         }
    ],
    "tags": ["Remake", "NoNG Song"],
    "song": "https://cdn.discordapp.com/attachments/1112151604070719699/1112422248431759431/1132880.mp3"
}
