{
    "id": 72191896,
    "name": "Vengeance",
    "author": "Kingcy2",
    "creators": [],
    "verifier": "crumche",
    "verification": "https://youtu.be/HdamGCpPHbM",
    "percentToQualify": 100,
    "password": "080421",
    "records": [
        {
            "user": "Samuuu",
            "link": "https://youtu.be/_CjsIfuSl9g",
            "percent": 100
        },
        {
            "user": "Jadrichiev",
            "link": "https://youtu.be/7vKQXrfkLm0",
            "percent": 100
        },
        {
            "user": "domi",
            "link": "https://youtu.be/ImqKjAzIx8o",
            "percent": 100
        }
    ],
    "tags": ["NoNG Song"]
}
